{
  "lexicon": 1,
  "id": "com.welistskyblue.list.like",
  "defs": {
    "main": {
      "type": "record",
      "description": "Record declaring a 'like' of a com.welistskyblue.list.item record.",
      "key": "tid",
      "record": {
        "type": "object",
        "required": [
          "subject",
          "createdAt"
        ],
        "properties": {
          "createdAt": {
            "type": "string",
            "format": "datetime"
          },
          "subject": {
            "type": "ref",
            "ref": "com.atproto.repo.strongRef"
          }
        }
      }
    }
  }
}